MANIFEST.in
README.txt
collective.getpid-configure.zcml
setup.py
collective/__init__.py
collective.getpid.egg-info/PKG-INFO
collective.getpid.egg-info/SOURCES.txt
collective.getpid.egg-info/dependency_links.txt
collective.getpid.egg-info/entry_points.txt
collective.getpid.egg-info/namespace_packages.txt
collective.getpid.egg-info/not-zip-safe
collective.getpid.egg-info/requires.txt
collective.getpid.egg-info/top_level.txt
collective/getpid/README.txt
collective/getpid/__init__.py
collective/getpid/browser.py
collective/getpid/configure.zcml
collective/getpid/test.zcml
collective/getpid/tests.py
collective/getpid/zope2.py
docs/HISTORY.txt