Metadata-Version: 1.0
Name: collective.getpid
Version: 0.1
Summary: GetPid of a zope process
Home-page: http://github.com/collective/collective.getpid
Author: yboussard
Author-email: yboussard@ingeniweb.com
License: GPL
Platform: UNKNOWN
Classifier: Programming Language :: Python
Classifier: Framework :: Zope2
